[
  {
    "startTime": 600012,
    "serverDuration": 1140022,
    "networkDuration": 1140022,
    "numClients": 1,
    "service": {
      "group": "com.bbn",
      "artifact": "simple-webserver_large-response",
      "version": "1"
    },
    "nodeLoad": {
      "TASK_CONTAINERS": 0.3
    },
    "networkLoad": {
      "DATARATE_TX": 0.2,
      "DATARATE_RX": 0.01
    }
  },
  {
    "startTime": 624012,
    "serverDuration": 1092021,
    "networkDuration": 1092021,
    "numClients": 1,
    "service": {
      "group": "com.bbn",
      "artifact": "simple-webserver_large-response",
      "version": "1"
    },
    "nodeLoad": {
      "TASK_CONTAINERS": 0.3
    },
    "networkLoad": {
      "DATARATE_TX": 0.2,
      "DATARATE_RX": 0.01
    }
  },
  {
    "startTime": 648012,
    "serverDuration": 1044020,
    "networkDuration": 1044020,
    "numClients": 1,
    "service": {
      "group": "com.bbn",
      "artifact": "simple-webserver_large-response",
      "version": "1"
    },
    "nodeLoad": {
      "TASK_CONTAINERS": 0.3
    },
    "networkLoad": {
      "DATARATE_TX": 0.2,
      "DATARATE_RX": 0.01
    }
  },
  {
    "startTime": 672013,
    "serverDuration": 996019,
    "networkDuration": 996019,
    "numClients": 1,
    "service": {
      "group": "com.bbn",
      "artifact": "simple-webserver_large-response",
      "version": "1"
    },
    "nodeLoad": {
      "TASK_CONTAINERS": 0.3
    },
    "networkLoad": {
      "DATARATE_TX": 0.2,
      "DATARATE_RX": 0.01
    }
  },
  {
    "startTime": 696013,
    "serverDuration": 948018,
    "networkDuration": 948018,
    "numClients": 1,
    "service": {
      "group": "com.bbn",
      "artifact": "simple-webserver_large-response",
      "version": "1"
    },
    "nodeLoad": {
      "TASK_CONTAINERS": 0.3
    },
    "networkLoad": {
      "DATARATE_TX": 0.2,
      "DATARATE_RX": 0.01
    }
  },
  {
    "startTime": 720014,
    "serverDuration": 900018,
    "networkDuration": 900018,
    "numClients": 1,
    "service": {
      "group": "com.bbn",
      "artifact": "simple-webserver_large-response",
      "version": "1"
    },
    "nodeLoad": {
      "TASK_CONTAINERS": 0.3
    },
    "networkLoad": {
      "DATARATE_TX": 0.2,
      "DATARATE_RX": 0.01
    }
  },
  {
    "startTime": 744014,
    "serverDuration": 852017,
    "networkDuration": 852017,
    "numClients": 1,
    "service": {
      "group": "com.bbn",
      "artifact": "simple-webserver_large-response",
      "version": "1"
    },
    "nodeLoad": {
      "TASK_CONTAINERS": 0.3
    },
    "networkLoad": {
      "DATARATE_TX": 0.2,
      "DATARATE_RX": 0.01
    }
  },
  {
    "startTime": 768015,
    "serverDuration": 804016,
    "networkDuration": 804016,
    "numClients": 1,
    "service": {
      "group": "com.bbn",
      "artifact": "simple-webserver_large-response",
      "version": "1"
    },
    "nodeLoad": {
      "TASK_CONTAINERS": 0.3
    },
    "networkLoad": {
      "DATARATE_TX": 0.2,
      "DATARATE_RX": 0.01
    }
  },
  {
    "startTime": 792015,
    "serverDuration": 756015,
    "networkDuration": 756015,
    "numClients": 1,
    "service": {
      "group": "com.bbn",
      "artifact": "simple-webserver_large-response",
      "version": "1"
    },
    "nodeLoad": {
      "TASK_CONTAINERS": 0.3
    },
    "networkLoad": {
      "DATARATE_TX": 0.2,
      "DATARATE_RX": 0.01
    }
  },
  {
    "startTime": 816016,
    "serverDuration": 708014,
    "networkDuration": 708014,
    "numClients": 1,
    "service": {
      "group": "com.bbn",
      "artifact": "simple-webserver_large-response",
      "version": "1"
    },
    "nodeLoad": {
      "TASK_CONTAINERS": 0.3
    },
    "networkLoad": {
      "DATARATE_TX": 0.2,
      "DATARATE_RX": 0.01
    }
  },
  {
    "startTime": 2040040,
    "serverDuration": 1140022,
    "networkDuration": 1140022,
    "numClients": 1,
    "service": {
      "group": "com.bbn",
      "artifact": "simple-webserver_large-response",
      "version": "1"
    },
    "nodeLoad": {
      "TASK_CONTAINERS": 0.3
    },
    "networkLoad": {
      "DATARATE_TX": 0.2,
      "DATARATE_RX": 0.01
    }
  },
  {
    "startTime": 2064041,
    "serverDuration": 1092021,
    "networkDuration": 1092021,
    "numClients": 1,
    "service": {
      "group": "com.bbn",
      "artifact": "simple-webserver_large-response",
      "version": "1"
    },
    "nodeLoad": {
      "TASK_CONTAINERS": 0.3
    },
    "networkLoad": {
      "DATARATE_TX": 0.2,
      "DATARATE_RX": 0.01
    }
  },
  {
    "startTime": 2088041,
    "serverDuration": 1044020,
    "networkDuration": 1044020,
    "numClients": 1,
    "service": {
      "group": "com.bbn",
      "artifact": "simple-webserver_large-response",
      "version": "1"
    },
    "nodeLoad": {
      "TASK_CONTAINERS": 0.3
    },
    "networkLoad": {
      "DATARATE_TX": 0.2,
      "DATARATE_RX": 0.01
    }
  },
  {
    "startTime": 2112042,
    "serverDuration": 996019,
    "networkDuration": 996019,
    "numClients": 1,
    "service": {
      "group": "com.bbn",
      "artifact": "simple-webserver_large-response",
      "version": "1"
    },
    "nodeLoad": {
      "TASK_CONTAINERS": 0.3
    },
    "networkLoad": {
      "DATARATE_TX": 0.2,
      "DATARATE_RX": 0.01
    }
  },
  {
    "startTime": 2136042,
    "serverDuration": 948018,
    "networkDuration": 948018,
    "numClients": 1,
    "service": {
      "group": "com.bbn",
      "artifact": "simple-webserver_large-response",
      "version": "1"
    },
    "nodeLoad": {
      "TASK_CONTAINERS": 0.3
    },
    "networkLoad": {
      "DATARATE_TX": 0.2,
      "DATARATE_RX": 0.01
    }
  },
  {
    "startTime": 2160043,
    "serverDuration": 900018,
    "networkDuration": 900018,
    "numClients": 1,
    "service": {
      "group": "com.bbn",
      "artifact": "simple-webserver_large-response",
      "version": "1"
    },
    "nodeLoad": {
      "TASK_CONTAINERS": 0.3
    },
    "networkLoad": {
      "DATARATE_TX": 0.2,
      "DATARATE_RX": 0.01
    }
  },
  {
    "startTime": 2184043,
    "serverDuration": 852017,
    "networkDuration": 852017,
    "numClients": 1,
    "service": {
      "group": "com.bbn",
      "artifact": "simple-webserver_large-response",
      "version": "1"
    },
    "nodeLoad": {
      "TASK_CONTAINERS": 0.3
    },
    "networkLoad": {
      "DATARATE_TX": 0.2,
      "DATARATE_RX": 0.01
    }
  },
  {
    "startTime": 2208044,
    "serverDuration": 804016,
    "networkDuration": 804016,
    "numClients": 1,
    "service": {
      "group": "com.bbn",
      "artifact": "simple-webserver_large-response",
      "version": "1"
    },
    "nodeLoad": {
      "TASK_CONTAINERS": 0.3
    },
    "networkLoad": {
      "DATARATE_TX": 0.2,
      "DATARATE_RX": 0.01
    }
  },
  {
    "startTime": 2232044,
    "serverDuration": 756015,
    "networkDuration": 756015,
    "numClients": 1,
    "service": {
      "group": "com.bbn",
      "artifact": "simple-webserver_large-response",
      "version": "1"
    },
    "nodeLoad": {
      "TASK_CONTAINERS": 0.3
    },
    "networkLoad": {
      "DATARATE_TX": 0.2,
      "DATARATE_RX": 0.01
    }
  },
  {
    "startTime": 2256045,
    "serverDuration": 708014,
    "networkDuration": 708014,
    "numClients": 1,
    "service": {
      "group": "com.bbn",
      "artifact": "simple-webserver_large-response",
      "version": "1"
    },
    "nodeLoad": {
      "TASK_CONTAINERS": 0.3
    },
    "networkLoad": {
      "DATARATE_TX": 0.2,
      "DATARATE_RX": 0.01
    }
  },
  {
    "startTime": 3480069,
    "serverDuration": 1140022,
    "networkDuration": 1140022,
    "numClients": 1,
    "service": {
      "group": "com.bbn",
      "artifact": "simple-webserver_large-response",
      "version": "1"
    },
    "nodeLoad": {
      "TASK_CONTAINERS": 0.3
    },
    "networkLoad": {
      "DATARATE_TX": 0.2,
      "DATARATE_RX": 0.01
    }
  },
  {
    "startTime": 3504070,
    "serverDuration": 1092021,
    "networkDuration": 1092021,
    "numClients": 1,
    "service": {
      "group": "com.bbn",
      "artifact": "simple-webserver_large-response",
      "version": "1"
    },
    "nodeLoad": {
      "TASK_CONTAINERS": 0.3
    },
    "networkLoad": {
      "DATARATE_TX": 0.2,
      "DATARATE_RX": 0.01
    }
  },
  {
    "startTime": 3528070,
    "serverDuration": 1044020,
    "networkDuration": 1044020,
    "numClients": 1,
    "service": {
      "group": "com.bbn",
      "artifact": "simple-webserver_large-response",
      "version": "1"
    },
    "nodeLoad": {
      "TASK_CONTAINERS": 0.3
    },
    "networkLoad": {
      "DATARATE_TX": 0.2,
      "DATARATE_RX": 0.01
    }
  },
  {
    "startTime": 3552071,
    "serverDuration": 996019,
    "networkDuration": 996019,
    "numClients": 1,
    "service": {
      "group": "com.bbn",
      "artifact": "simple-webserver_large-response",
      "version": "1"
    },
    "nodeLoad": {
      "TASK_CONTAINERS": 0.3
    },
    "networkLoad": {
      "DATARATE_TX": 0.2,
      "DATARATE_RX": 0.01
    }
  },
  {
    "startTime": 3576071,
    "serverDuration": 948018,
    "networkDuration": 948018,
    "numClients": 1,
    "service": {
      "group": "com.bbn",
      "artifact": "simple-webserver_large-response",
      "version": "1"
    },
    "nodeLoad": {
      "TASK_CONTAINERS": 0.3
    },
    "networkLoad": {
      "DATARATE_TX": 0.2,
      "DATARATE_RX": 0.01
    }
  },
  {
    "startTime": 3600072,
    "serverDuration": 900018,
    "networkDuration": 900018,
    "numClients": 1,
    "service": {
      "group": "com.bbn",
      "artifact": "simple-webserver_large-response",
      "version": "1"
    },
    "nodeLoad": {
      "TASK_CONTAINERS": 0.3
    },
    "networkLoad": {
      "DATARATE_TX": 0.2,
      "DATARATE_RX": 0.01
    }
  },
  {
    "startTime": 3624072,
    "serverDuration": 852017,
    "networkDuration": 852017,
    "numClients": 1,
    "service": {
      "group": "com.bbn",
      "artifact": "simple-webserver_large-response",
      "version": "1"
    },
    "nodeLoad": {
      "TASK_CONTAINERS": 0.3
    },
    "networkLoad": {
      "DATARATE_TX": 0.2,
      "DATARATE_RX": 0.01
    }
  },
  {
    "startTime": 3648072,
    "serverDuration": 804016,
    "networkDuration": 804016,
    "numClients": 1,
    "service": {
      "group": "com.bbn",
      "artifact": "simple-webserver_large-response",
      "version": "1"
    },
    "nodeLoad": {
      "TASK_CONTAINERS": 0.3
    },
    "networkLoad": {
      "DATARATE_TX": 0.2,
      "DATARATE_RX": 0.01
    }
  },
  {
    "startTime": 3672073,
    "serverDuration": 756015,
    "networkDuration": 756015,
    "numClients": 1,
    "service": {
      "group": "com.bbn",
      "artifact": "simple-webserver_large-response",
      "version": "1"
    },
    "nodeLoad": {
      "TASK_CONTAINERS": 0.3
    },
    "networkLoad": {
      "DATARATE_TX": 0.2,
      "DATARATE_RX": 0.01
    }
  },
  {
    "startTime": 3696073,
    "serverDuration": 708014,
    "networkDuration": 708014,
    "numClients": 1,
    "service": {
      "group": "com.bbn",
      "artifact": "simple-webserver_large-response",
      "version": "1"
    },
    "nodeLoad": {
      "TASK_CONTAINERS": 0.3
    },
    "networkLoad": {
      "DATARATE_TX": 0.2,
      "DATARATE_RX": 0.01
    }
  },
  {
    "startTime": 4920098,
    "serverDuration": 1140022,
    "networkDuration": 1140022,
    "numClients": 1,
    "service": {
      "group": "com.bbn",
      "artifact": "simple-webserver_large-response",
      "version": "1"
    },
    "nodeLoad": {
      "TASK_CONTAINERS": 0.3
    },
    "networkLoad": {
      "DATARATE_TX": 0.2,
      "DATARATE_RX": 0.01
    }
  },
  {
    "startTime": 4944098,
    "serverDuration": 1092021,
    "networkDuration": 1092021,
    "numClients": 1,
    "service": {
      "group": "com.bbn",
      "artifact": "simple-webserver_large-response",
      "version": "1"
    },
    "nodeLoad": {
      "TASK_CONTAINERS": 0.3
    },
    "networkLoad": {
      "DATARATE_TX": 0.2,
      "DATARATE_RX": 0.01
    }
  },
  {
    "startTime": 4968099,
    "serverDuration": 1044020,
    "networkDuration": 1044020,
    "numClients": 1,
    "service": {
      "group": "com.bbn",
      "artifact": "simple-webserver_large-response",
      "version": "1"
    },
    "nodeLoad": {
      "TASK_CONTAINERS": 0.3
    },
    "networkLoad": {
      "DATARATE_TX": 0.2,
      "DATARATE_RX": 0.01
    }
  },
  {
    "startTime": 4992099,
    "serverDuration": 996019,
    "networkDuration": 996019,
    "numClients": 1,
    "service": {
      "group": "com.bbn",
      "artifact": "simple-webserver_large-response",
      "version": "1"
    },
    "nodeLoad": {
      "TASK_CONTAINERS": 0.3
    },
    "networkLoad": {
      "DATARATE_TX": 0.2,
      "DATARATE_RX": 0.01
    }
  },
  {
    "startTime": 5016100,
    "serverDuration": 948018,
    "networkDuration": 948018,
    "numClients": 1,
    "service": {
      "group": "com.bbn",
      "artifact": "simple-webserver_large-response",
      "version": "1"
    },
    "nodeLoad": {
      "TASK_CONTAINERS": 0.3
    },
    "networkLoad": {
      "DATARATE_TX": 0.2,
      "DATARATE_RX": 0.01
    }
  },
  {
    "startTime": 5040100,
    "serverDuration": 900018,
    "networkDuration": 900018,
    "numClients": 1,
    "service": {
      "group": "com.bbn",
      "artifact": "simple-webserver_large-response",
      "version": "1"
    },
    "nodeLoad": {
      "TASK_CONTAINERS": 0.3
    },
    "networkLoad": {
      "DATARATE_TX": 0.2,
      "DATARATE_RX": 0.01
    }
  },
  {
    "startTime": 5064101,
    "serverDuration": 852017,
    "networkDuration": 852017,
    "numClients": 1,
    "service": {
      "group": "com.bbn",
      "artifact": "simple-webserver_large-response",
      "version": "1"
    },
    "nodeLoad": {
      "TASK_CONTAINERS": 0.3
    },
    "networkLoad": {
      "DATARATE_TX": 0.2,
      "DATARATE_RX": 0.01
    }
  },
  {
    "startTime": 5088101,
    "serverDuration": 804016,
    "networkDuration": 804016,
    "numClients": 1,
    "service": {
      "group": "com.bbn",
      "artifact": "simple-webserver_large-response",
      "version": "1"
    },
    "nodeLoad": {
      "TASK_CONTAINERS": 0.3
    },
    "networkLoad": {
      "DATARATE_TX": 0.2,
      "DATARATE_RX": 0.01
    }
  },
  {
    "startTime": 5112102,
    "serverDuration": 756015,
    "networkDuration": 756015,
    "numClients": 1,
    "service": {
      "group": "com.bbn",
      "artifact": "simple-webserver_large-response",
      "version": "1"
    },
    "nodeLoad": {
      "TASK_CONTAINERS": 0.3
    },
    "networkLoad": {
      "DATARATE_TX": 0.2,
      "DATARATE_RX": 0.01
    }
  },
  {
    "startTime": 5136102,
    "serverDuration": 708014,
    "networkDuration": 708014,
    "numClients": 1,
    "service": {
      "group": "com.bbn",
      "artifact": "simple-webserver_large-response",
      "version": "1"
    },
    "nodeLoad": {
      "TASK_CONTAINERS": 0.3
    },
    "networkLoad": {
      "DATARATE_TX": 0.2,
      "DATARATE_RX": 0.01
    }
  },
  {
    "startTime": 6360127,
    "serverDuration": 1140022,
    "networkDuration": 1140022,
    "numClients": 1,
    "service": {
      "group": "com.bbn",
      "artifact": "simple-webserver_large-response",
      "version": "1"
    },
    "nodeLoad": {
      "TASK_CONTAINERS": 0.3
    },
    "networkLoad": {
      "DATARATE_TX": 0.2,
      "DATARATE_RX": 0.01
    }
  },
  {
    "startTime": 6384127,
    "serverDuration": 1092021,
    "networkDuration": 1092021,
    "numClients": 1,
    "service": {
      "group": "com.bbn",
      "artifact": "simple-webserver_large-response",
      "version": "1"
    },
    "nodeLoad": {
      "TASK_CONTAINERS": 0.3
    },
    "networkLoad": {
      "DATARATE_TX": 0.2,
      "DATARATE_RX": 0.01
    }
  },
  {
    "startTime": 6408128,
    "serverDuration": 1044020,
    "networkDuration": 1044020,
    "numClients": 1,
    "service": {
      "group": "com.bbn",
      "artifact": "simple-webserver_large-response",
      "version": "1"
    },
    "nodeLoad": {
      "TASK_CONTAINERS": 0.3
    },
    "networkLoad": {
      "DATARATE_TX": 0.2,
      "DATARATE_RX": 0.01
    }
  },
  {
    "startTime": 6432128,
    "serverDuration": 996019,
    "networkDuration": 996019,
    "numClients": 1,
    "service": {
      "group": "com.bbn",
      "artifact": "simple-webserver_large-response",
      "version": "1"
    },
    "nodeLoad": {
      "TASK_CONTAINERS": 0.3
    },
    "networkLoad": {
      "DATARATE_TX": 0.2,
      "DATARATE_RX": 0.01
    }
  },
  {
    "startTime": 6456129,
    "serverDuration": 948018,
    "networkDuration": 948018,
    "numClients": 1,
    "service": {
      "group": "com.bbn",
      "artifact": "simple-webserver_large-response",
      "version": "1"
    },
    "nodeLoad": {
      "TASK_CONTAINERS": 0.3
    },
    "networkLoad": {
      "DATARATE_TX": 0.2,
      "DATARATE_RX": 0.01
    }
  },
  {
    "startTime": 6480129,
    "serverDuration": 900018,
    "networkDuration": 900018,
    "numClients": 1,
    "service": {
      "group": "com.bbn",
      "artifact": "simple-webserver_large-response",
      "version": "1"
    },
    "nodeLoad": {
      "TASK_CONTAINERS": 0.3
    },
    "networkLoad": {
      "DATARATE_TX": 0.2,
      "DATARATE_RX": 0.01
    }
  },
  {
    "startTime": 6504130,
    "serverDuration": 852017,
    "networkDuration": 852017,
    "numClients": 1,
    "service": {
      "group": "com.bbn",
      "artifact": "simple-webserver_large-response",
      "version": "1"
    },
    "nodeLoad": {
      "TASK_CONTAINERS": 0.3
    },
    "networkLoad": {
      "DATARATE_TX": 0.2,
      "DATARATE_RX": 0.01
    }
  },
  {
    "startTime": 6528130,
    "serverDuration": 804016,
    "networkDuration": 804016,
    "numClients": 1,
    "service": {
      "group": "com.bbn",
      "artifact": "simple-webserver_large-response",
      "version": "1"
    },
    "nodeLoad": {
      "TASK_CONTAINERS": 0.3
    },
    "networkLoad": {
      "DATARATE_TX": 0.2,
      "DATARATE_RX": 0.01
    }
  },
  {
    "startTime": 6552131,
    "serverDuration": 756015,
    "networkDuration": 756015,
    "numClients": 1,
    "service": {
      "group": "com.bbn",
      "artifact": "simple-webserver_large-response",
      "version": "1"
    },
    "nodeLoad": {
      "TASK_CONTAINERS": 0.3
    },
    "networkLoad": {
      "DATARATE_TX": 0.2,
      "DATARATE_RX": 0.01
    }
  },
  {
    "startTime": 6576131,
    "serverDuration": 708014,
    "networkDuration": 708014,
    "numClients": 1,
    "service": {
      "group": "com.bbn",
      "artifact": "simple-webserver_large-response",
      "version": "1"
    },
    "nodeLoad": {
      "TASK_CONTAINERS": 0.3
    },
    "networkLoad": {
      "DATARATE_TX": 0.2,
      "DATARATE_RX": 0.01
    }
  },
  {
    "startTime": 7800156,
    "serverDuration": 1140022,
    "networkDuration": 1140022,
    "numClients": 1,
    "service": {
      "group": "com.bbn",
      "artifact": "simple-webserver_large-response",
      "version": "1"
    },
    "nodeLoad": {
      "TASK_CONTAINERS": 0.3
    },
    "networkLoad": {
      "DATARATE_TX": 0.2,
      "DATARATE_RX": 0.01
    }
  },
  {
    "startTime": 7824156,
    "serverDuration": 1092021,
    "networkDuration": 1092021,
    "numClients": 1,
    "service": {
      "group": "com.bbn",
      "artifact": "simple-webserver_large-response",
      "version": "1"
    },
    "nodeLoad": {
      "TASK_CONTAINERS": 0.3
    },
    "networkLoad": {
      "DATARATE_TX": 0.2,
      "DATARATE_RX": 0.01
    }
  },
  {
    "startTime": 7848156,
    "serverDuration": 1044020,
    "networkDuration": 1044020,
    "numClients": 1,
    "service": {
      "group": "com.bbn",
      "artifact": "simple-webserver_large-response",
      "version": "1"
    },
    "nodeLoad": {
      "TASK_CONTAINERS": 0.3
    },
    "networkLoad": {
      "DATARATE_TX": 0.2,
      "DATARATE_RX": 0.01
    }
  },
  {
    "startTime": 7872157,
    "serverDuration": 996019,
    "networkDuration": 996019,
    "numClients": 1,
    "service": {
      "group": "com.bbn",
      "artifact": "simple-webserver_large-response",
      "version": "1"
    },
    "nodeLoad": {
      "TASK_CONTAINERS": 0.3
    },
    "networkLoad": {
      "DATARATE_TX": 0.2,
      "DATARATE_RX": 0.01
    }
  },
  {
    "startTime": 7896157,
    "serverDuration": 948018,
    "networkDuration": 948018,
    "numClients": 1,
    "service": {
      "group": "com.bbn",
      "artifact": "simple-webserver_large-response",
      "version": "1"
    },
    "nodeLoad": {
      "TASK_CONTAINERS": 0.3
    },
    "networkLoad": {
      "DATARATE_TX": 0.2,
      "DATARATE_RX": 0.01
    }
  },
  {
    "startTime": 7920158,
    "serverDuration": 900018,
    "networkDuration": 900018,
    "numClients": 1,
    "service": {
      "group": "com.bbn",
      "artifact": "simple-webserver_large-response",
      "version": "1"
    },
    "nodeLoad": {
      "TASK_CONTAINERS": 0.3
    },
    "networkLoad": {
      "DATARATE_TX": 0.2,
      "DATARATE_RX": 0.01
    }
  },
  {
    "startTime": 7944158,
    "serverDuration": 852017,
    "networkDuration": 852017,
    "numClients": 1,
    "service": {
      "group": "com.bbn",
      "artifact": "simple-webserver_large-response",
      "version": "1"
    },
    "nodeLoad": {
      "TASK_CONTAINERS": 0.3
    },
    "networkLoad": {
      "DATARATE_TX": 0.2,
      "DATARATE_RX": 0.01
    }
  },
  {
    "startTime": 7968159,
    "serverDuration": 804016,
    "networkDuration": 804016,
    "numClients": 1,
    "service": {
      "group": "com.bbn",
      "artifact": "simple-webserver_large-response",
      "version": "1"
    },
    "nodeLoad": {
      "TASK_CONTAINERS": 0.3
    },
    "networkLoad": {
      "DATARATE_TX": 0.2,
      "DATARATE_RX": 0.01
    }
  },
  {
    "startTime": 7992159,
    "serverDuration": 756015,
    "networkDuration": 756015,
    "numClients": 1,
    "service": {
      "group": "com.bbn",
      "artifact": "simple-webserver_large-response",
      "version": "1"
    },
    "nodeLoad": {
      "TASK_CONTAINERS": 0.3
    },
    "networkLoad": {
      "DATARATE_TX": 0.2,
      "DATARATE_RX": 0.01
    }
  },
  {
    "startTime": 8016160,
    "serverDuration": 708014,
    "networkDuration": 708014,
    "numClients": 1,
    "service": {
      "group": "com.bbn",
      "artifact": "simple-webserver_large-response",
      "version": "1"
    },
    "nodeLoad": {
      "TASK_CONTAINERS": 0.3
    },
    "networkLoad": {
      "DATARATE_TX": 0.2,
      "DATARATE_RX": 0.01
    }
  },
  {
    "startTime": 9240184,
    "serverDuration": 1140022,
    "networkDuration": 1140022,
    "numClients": 1,
    "service": {
      "group": "com.bbn",
      "artifact": "simple-webserver_large-response",
      "version": "1"
    },
    "nodeLoad": {
      "TASK_CONTAINERS": 0.3
    },
    "networkLoad": {
      "DATARATE_TX": 0.2,
      "DATARATE_RX": 0.01
    }
  },
  {
    "startTime": 9264185,
    "serverDuration": 1092021,
    "networkDuration": 1092021,
    "numClients": 1,
    "service": {
      "group": "com.bbn",
      "artifact": "simple-webserver_large-response",
      "version": "1"
    },
    "nodeLoad": {
      "TASK_CONTAINERS": 0.3
    },
    "networkLoad": {
      "DATARATE_TX": 0.2,
      "DATARATE_RX": 0.01
    }
  },
  {
    "startTime": 9288185,
    "serverDuration": 1044020,
    "networkDuration": 1044020,
    "numClients": 1,
    "service": {
      "group": "com.bbn",
      "artifact": "simple-webserver_large-response",
      "version": "1"
    },
    "nodeLoad": {
      "TASK_CONTAINERS": 0.3
    },
    "networkLoad": {
      "DATARATE_TX": 0.2,
      "DATARATE_RX": 0.01
    }
  },
  {
    "startTime": 9312186,
    "serverDuration": 996019,
    "networkDuration": 996019,
    "numClients": 1,
    "service": {
      "group": "com.bbn",
      "artifact": "simple-webserver_large-response",
      "version": "1"
    },
    "nodeLoad": {
      "TASK_CONTAINERS": 0.3
    },
    "networkLoad": {
      "DATARATE_TX": 0.2,
      "DATARATE_RX": 0.01
    }
  },
  {
    "startTime": 9336186,
    "serverDuration": 948018,
    "networkDuration": 948018,
    "numClients": 1,
    "service": {
      "group": "com.bbn",
      "artifact": "simple-webserver_large-response",
      "version": "1"
    },
    "nodeLoad": {
      "TASK_CONTAINERS": 0.3
    },
    "networkLoad": {
      "DATARATE_TX": 0.2,
      "DATARATE_RX": 0.01
    }
  },
  {
    "startTime": 9360187,
    "serverDuration": 900018,
    "networkDuration": 900018,
    "numClients": 1,
    "service": {
      "group": "com.bbn",
      "artifact": "simple-webserver_large-response",
      "version": "1"
    },
    "nodeLoad": {
      "TASK_CONTAINERS": 0.3
    },
    "networkLoad": {
      "DATARATE_TX": 0.2,
      "DATARATE_RX": 0.01
    }
  },
  {
    "startTime": 9384187,
    "serverDuration": 852017,
    "networkDuration": 852017,
    "numClients": 1,
    "service": {
      "group": "com.bbn",
      "artifact": "simple-webserver_large-response",
      "version": "1"
    },
    "nodeLoad": {
      "TASK_CONTAINERS": 0.3
    },
    "networkLoad": {
      "DATARATE_TX": 0.2,
      "DATARATE_RX": 0.01
    }
  },
  {
    "startTime": 9408188,
    "serverDuration": 804016,
    "networkDuration": 804016,
    "numClients": 1,
    "service": {
      "group": "com.bbn",
      "artifact": "simple-webserver_large-response",
      "version": "1"
    },
    "nodeLoad": {
      "TASK_CONTAINERS": 0.3
    },
    "networkLoad": {
      "DATARATE_TX": 0.2,
      "DATARATE_RX": 0.01
    }
  },
  {
    "startTime": 9432188,
    "serverDuration": 756015,
    "networkDuration": 756015,
    "numClients": 1,
    "service": {
      "group": "com.bbn",
      "artifact": "simple-webserver_large-response",
      "version": "1"
    },
    "nodeLoad": {
      "TASK_CONTAINERS": 0.3
    },
    "networkLoad": {
      "DATARATE_TX": 0.2,
      "DATARATE_RX": 0.01
    }
  },
  {
    "startTime": 9456189,
    "serverDuration": 708014,
    "networkDuration": 708014,
    "numClients": 1,
    "service": {
      "group": "com.bbn",
      "artifact": "simple-webserver_large-response",
      "version": "1"
    },
    "nodeLoad": {
      "TASK_CONTAINERS": 0.3
    },
    "networkLoad": {
      "DATARATE_TX": 0.2,
      "DATARATE_RX": 0.01
    }
  }
]